beamformer/__init__.py
beamformer/beamformer.py
beamformer/cli.py
beamformer-0.1.0.dist-info/METADATA
beamformer-0.1.0.dist-info/RECORD
beamformer-0.1.0.dist-info/WHEEL
beamformer-0.1.0.dist-info/entry_points.txt
beamformer-0.1.0.dist-info/top_level.txt
