Metadata-Version: 2.1
Name: beamformer
Version: 0.1.0
Summary: Beam pattern synthesis python API
Home-page: https://github.com/semink/beamformer
Author: Semin Kwak
Author-email: semin.kwak@epfl.ch
License: MIT license
Keywords: beamformer
Platform: UNKNOWN
Classifier: Development Status :: 2 - Pre-Alpha
Classifier: Intended Audience :: Developers
Classifier: License :: OSI Approved :: MIT License
Classifier: Natural Language :: English
Classifier: Programming Language :: Python :: 2
Classifier: Programming Language :: Python :: 2.7
Classifier: Programming Language :: Python :: 3
Classifier: Programming Language :: Python :: 3.4
Classifier: Programming Language :: Python :: 3.5
Classifier: Programming Language :: Python :: 3.6
Classifier: Programming Language :: Python :: 3.7
Requires-Dist: Click (>=6.0)
